devns/__init__.py
devns/cli.py
devns/config.py
devns/dns.py
devns/server.py
devns-0.5.0.dist-info/METADATA
devns-0.5.0.dist-info/RECORD
devns-0.5.0.dist-info/WHEEL
devns-0.5.0.dist-info/entry_points.txt
devns-0.5.0.dist-info/top_level.txt
devns-0.5.0.dist-info/zip-safe
