Metadata-Version: 2.1
Name: devns
Version: 0.5.0
Summary: Pure Python DNS server for developers
Home-page: https://github.com/daveisadork/PyDevNS
Author: Dave Hayes
Author-email: dwhayes@gmail.com
License: MIT License
Keywords: dns
Platform: UNKNOWN
Classifier: Development Status :: 1 - Planning
Classifier: Environment :: Console
Classifier: Environment :: No Input/Output (Daemon)
Classifier: Intended Audience :: Developers
Classifier: License :: OSI Approved :: MIT License
Classifier: Programming Language :: Python
Classifier: Programming Language :: Python :: 2.6
Classifier: Programming Language :: Python :: 2.7
Classifier: Programming Language :: Python :: 3.3
Classifier: Programming Language :: Python :: 3.4
Classifier: Programming Language :: Python :: 3.5
Classifier: Programming Language :: Python :: 3.6
Classifier: Programming Language :: Python :: Implementation :: CPython
Classifier: Programming Language :: Python :: Implementation :: PyPy
Classifier: Topic :: Internet
Classifier: Topic :: Internet :: Name Service (DNS)
Classifier: Topic :: Software Development
Classifier: Topic :: System
Classifier: Topic :: System :: Networking
Classifier: Topic :: Utilities
Requires-Dist: future
Requires-Dist: six
